watch_tmux_attached/__init__.py
watch_tmux_attached/__main__.py
watch_tmux_attached/cli.py
watch_tmux_attached/watch_tmux_attached.py
aw_watcher_tmux_attached-0.0.1.dist-info/METADATA
aw_watcher_tmux_attached-0.0.1.dist-info/WHEEL
aw_watcher_tmux_attached-0.0.1.dist-info/entry_points.txt
aw_watcher_tmux_attached-0.0.1.dist-info/licenses/LICENSE.txt
aw_watcher_tmux_attached-0.0.1.dist-info/RECORD
