Metadata-Version: 2.3
Name: aw-watcher-tmux-attached
Version: 0.0.1
Summary: ActivityWatch watcher for attached Tmux sessions
Project-URL: Homepage, https://github.com/patrislav1/aw-watcher-tmux-attached
Author-email: Patrick Huesmann <info@patrick-huesmann.de>
License-File: LICENSE.txt
Requires-Python: >=3.6
Requires-Dist: aw-client
Requires-Dist: libtmux
